trialblazer/__init__.py
trialblazer/__main__.py
trialblazer/models.py
trialblazer/trialblazer.py
trialblazer/trialtrainer.py
trialblazer/Dataset_characterization/physicochem_properties_calculation.py
trialblazer/Dataset_preprocess/clinicaltrial_preprocess.py
trialblazer/Dataset_preprocess/name_extraction_Smilesmatching.py
trialblazer/Dataset_preprocess/Preprocess_compound/Preprocess_FoodDB.py
trialblazer/Dataset_preprocess/Preprocess_compound/preprocess_molecules.py
trialblazer/Dataset_preprocess/Preprocess_compound/remove_duplicate.py
trialblazer/Dataset_preprocess/Preprocess_compound/separate_multicomponents_test.py
trialblazer/Dataset_preprocess/Preprocess_compound/split_files.py
trialblazer/Descriptor_calculation/process_similarity_results.py
trialblazer/Descriptor_calculation/process_target_features.py
trialblazer/Descriptor_calculation/similarity_based_target_calculation.py
trialblazer/Model/testset_visualization.py
trialblazer/Nerdd/__init__.py
trialblazer/Nerdd/trialblazer_model.py
trialblazer/data/logo.svg
trialblazer/data/logo_vienna.gif
trialblazer/data/nerdd.yml
trialblazer-0.2.0.dist-info/licenses/LICENSE
trialblazer-0.2.0.dist-info/METADATA
trialblazer-0.2.0.dist-info/WHEEL
trialblazer-0.2.0.dist-info/entry_points.txt
trialblazer-0.2.0.dist-info/top_level.txt
trialblazer-0.2.0.dist-info/RECORD
