Metadata-Version: 2.4
Name: trialblazer
Version: 0.2.0
Summary: A Chemistry-Focused Predictor of Toxicity Risks in Late-Stage Drug Development
Author-email: Huanni Zhang <huanni.zhang@univie.ac.at>, William Schueller <william.schueller@univie.ac.at>
License: MIT License
Project-URL: Repository, https://github.com/molinfo-vienna/trialblazer
Project-URL: Issues, https://github.com/molinfo-vienna/trialblazer/issues
Project-URL: ReadTheDocs, https://trialblazer.readthedocs.io
Keywords: chemoinformatics,scientific software,chemistry,drug discovery,toxicity
Classifier: Development Status :: 2 - Pre-Alpha
Classifier: Intended Audience :: Developers
Classifier: Intended Audience :: Science/Research
Classifier: Natural Language :: English
Classifier: Programming Language :: Python :: 3
Classifier: Programming Language :: Python :: 3.10
Classifier: Programming Language :: Python :: 3.11
Classifier: Programming Language :: Python :: 3.12
Requires-Python: >=3.8
License-File: LICENSE
Requires-Dist: click
Requires-Dist: pandas
Requires-Dist: requests
Requires-Dist: rdkit==2024.09.6
Requires-Dist: numpy
Requires-Dist: scikit-learn
Requires-Dist: seaborn
Requires-Dist: matplotlib
Requires-Dist: psutil
Requires-Dist: joblib
Requires-Dist: pyzmq
Requires-Dist: acm-hamburg-legacy
Requires-Dist: chembl_structure_pipeline
Requires-Dist: fpsim2
Requires-Dist: cirpy
Provides-Extra: dev
Requires-Dist: build; extra == "dev"
Requires-Dist: bump-my-version; extra == "dev"
Requires-Dist: coverage[toml]; extra == "dev"
Requires-Dist: pytest; extra == "dev"
Requires-Dist: pytest-cov; extra == "dev"
Requires-Dist: ruff; extra == "dev"
Requires-Dist: sphinx; extra == "dev"
Requires-Dist: sphinx_rtd_theme; extra == "dev"
Requires-Dist: sphinx-autoapi; extra == "dev"
Requires-Dist: tox; extra == "dev"
Requires-Dist: myst_parser; extra == "dev"
Provides-Extra: docs
Requires-Dist: sphinx; extra == "docs"
Requires-Dist: sphinx_rtd_theme; extra == "docs"
Requires-Dist: sphinx-autoapi; extra == "docs"
Requires-Dist: myst_parser; extra == "docs"
Provides-Extra: publishing
Requires-Dist: build; extra == "publishing"
Requires-Dist: twine; extra == "publishing"
Requires-Dist: wheel; extra == "publishing"
Dynamic: license-file
